MANIFEST.in
setup.py
docs/HISTORY.txt
src/dolmen/__init__.py
src/dolmen.app.security.egg-info/PKG-INFO
src/dolmen.app.security.egg-info/SOURCES.txt
src/dolmen.app.security.egg-info/dependency_links.txt
src/dolmen.app.security.egg-info/namespace_packages.txt
src/dolmen.app.security.egg-info/not-zip-safe
src/dolmen.app.security.egg-info/requires.txt
src/dolmen.app.security.egg-info/top_level.txt
src/dolmen/app/__init__.py
src/dolmen/app/security/README.txt
src/dolmen/app/security/__init__.py
src/dolmen/app/security/configure.zcml
src/dolmen/app/security/content.py
src/dolmen/app/security/roles.py
src/dolmen/app/security/tests.py